{
  "test": "cardsort",
  "version": "1.0",
  "description": "CARDSORT Test",
  "parameters": [
    {
      "name": "repeats",
      "type": "integer",
      "default": 2,
      "description": "Number of repetitions through the deck. Default of 2 is akin to BCST-128, whereas 1 would be like BCST-64.  See alternate bcst-64.pbl for version specifically targetting WCST64."
    },
    {
      "name": "runlength",
      "type": "integer",
      "default": 10,
      "description": "Number of correct responses required before switching categories.  Typically, 10 are used, although 5 is also common."
    },
    {
      "name": "useCanonical",
      "type": "boolean",
      "default": 1,
      "description": "Whether the canonical stimulus card piles should be used. If 0, cards will be chosen randomly.",
      "options": [
        0,
        1
      ]
    },
    {
      "name": "useReduced",
      "type": "boolean",
      "default": 0,
      "description": "Whether Nelson's 24-card non-redundant deck (modified card sort) should be used. If non-zero, the 24-card deck will be used.",
      "options": [
        0,
        1
      ]
    },
    {
      "name": "rulefeedback",
      "type": "boolean",
      "default": 0,
      "description": "Whether feedback should be given when the rule changes. If non-zero, feedback will be given.",
      "options": [
        0,
        1
      ]
    },
    {
      "name": "usemouse",
      "type": "boolean",
      "default": 1,
      "description": "Whether the mouse should be used to control the test.  If 0, keyboard keys will be used. If non-zero, mouse will be used.",
      "options": [
        0,
        1
      ]
    }
  ]
}