{
  "test": "mathproc",
  "version": "1.0",
  "description": "MATHPROC Test",
  "parameters": [
    {
      "name": "blocktime",
      "type": "integer",
      "default": 180,
      "description": "Duration of block in sec (default should be  3 min)"
    },
    {
      "name": "uselength1",
      "type": "boolean",
      "default": 0,
      "description": "Should length 1 be used (sort of a control condition)",
      "options": [
        0,
        1
      ]
    },
    {
      "name": "uselength2",
      "type": "boolean",
      "default": 1,
      "description": "Sholud length 2 problems be used?",
      "options": [
        0,
        1
      ]
    },
    {
      "name": "uselength3",
      "type": "boolean",
      "default": 1,
      "description": "Should length 3 problems be used?",
      "options": [
        0,
        1
      ]
    },
    {
      "name": "uselength4",
      "type": "boolean",
      "default": 1,
      "description": "Should length 4 problems be used?",
      "options": [
        0,
        1
      ]
    },
    {
      "name": "uselength5",
      "type": "boolean",
      "default": 0,
      "description": "Should length 5 problems be used?",
      "options": [
        0,
        1
      ]
    },
    {
      "name": "deadline1",
      "type": "integer",
      "default": 1500,
      "description": "Deadline in ms for length-1 problems"
    },
    {
      "name": "deadline2",
      "type": "integer",
      "default": 1500,
      "description": "Deadline in ms for length-2 problems"
    },
    {
      "name": "deadline3",
      "type": "integer",
      "default": 3000,
      "description": "Deadline in ms for length-3 problems"
    },
    {
      "name": "deadline4",
      "type": "integer",
      "default": 4000,
      "description": "Deadline in ms for length-4 problems"
    },
    {
      "name": "deadline5",
      "type": "integer",
      "default": 5000,
      "description": "Deadline in ms for length-5 problems"
    },
    {
      "name": "minsum",
      "type": "boolean",
      "default": 1,
      "description": "Smallest sum to use",
      "options": [
        0,
        1
      ]
    },
    {
      "name": "maxsum",
      "type": "integer",
      "default": 9,
      "description": "Largest sum to use"
    },
    {
      "name": "givefeedback",
      "type": "boolean",
      "default": 1,
      "description": "Whether correct/incorrect feedback should be given",
      "options": [
        0,
        1
      ]
    },
    {
      "name": "randomizeblocks",
      "type": "boolean",
      "default": 0,
      "description": "Should order of blocks be randomized?",
      "options": [
        0,
        1
      ]
    }
  ]
}